allscreenshots_og_screenshot/__init__.py
allscreenshots_og_screenshot/plugin.py
mkdocs_allscreenshots_og_screenshot-0.1.1.dist-info/METADATA
mkdocs_allscreenshots_og_screenshot-0.1.1.dist-info/WHEEL
mkdocs_allscreenshots_og_screenshot-0.1.1.dist-info/entry_points.txt
mkdocs_allscreenshots_og_screenshot-0.1.1.dist-info/top_level.txt
mkdocs_allscreenshots_og_screenshot-0.1.1.dist-info/RECORD
