Metadata-Version: 2.4
Name: mkdocs-allscreenshots-og-screenshot
Version: 0.1.1
Summary: MkDocs plugin for dynamic OpenGraph images via Allscreenshots API
Project-URL: Homepage, https://allscreenshots.com
Requires-Python: >=3.8
Requires-Dist: mkdocs>=1.0
